pi_si7021
