Metadata-Version: 2.1
Name: pi-si7021
Version: 0.5.4
Summary: Library to read si7021 sensor.
Home-page: https://github.com/kangasta/pi_si7021
Author: Toni Kangas
License: UNKNOWN
Platform: UNKNOWN
Classifier: Programming Language :: Python :: 3
Classifier: License :: OSI Approved :: MIT License
Classifier: Operating System :: OS Independent
